pyeqx/opentelemetry/__init__.py
pyeqx/opentelemetry/config.py
pyeqx/opentelemetry/constants.py
pyeqx/opentelemetry/instrumentation.py
pyeqx/opentelemetry/spark.py
pyeqx/opentelemetry/exporters/__init__.py
pyeqx/opentelemetry/exporters/azure_monitor_exporter.py
pyeqx/opentelemetry/exporters/otlp_exporter.py
pyeqx_opentelemetry-0.4.2.dist-info/METADATA
pyeqx_opentelemetry-0.4.2.dist-info/WHEEL
pyeqx_opentelemetry-0.4.2.dist-info/top_level.txt
pyeqx_opentelemetry-0.4.2.dist-info/RECORD
