Metadata-Version: 2.4
Name: pyeqx-opentelemetry
Version: 0.4.2
Summary: OpenTelemetry instrumentation for PyEQX
Author: ESBM Cronus
Classifier: Programming Language :: Python :: 3
Requires-Python: >=3.12
Requires-Dist: opentelemetry-api
Requires-Dist: opentelemetry-exporter-otlp
Requires-Dist: opentelemetry-exporter-prometheus
Requires-Dist: opentelemetry-instrumentation
Requires-Dist: opentelemetry-sdk
Requires-Dist: azure-monitor-opentelemetry-exporter==1.0.0b46
Provides-Extra: dev
Requires-Dist: black; extra == "dev"
Requires-Dist: ruff; extra == "dev"
Requires-Dist: build; extra == "dev"
Requires-Dist: twine; extra == "dev"
Requires-Dist: python-dotenv; extra == "dev"
Requires-Dist: pytest; extra == "dev"
Requires-Dist: pytest-cov; extra == "dev"
Requires-Dist: pytest-mock; extra == "dev"
Requires-Dist: pytest-watch; extra == "dev"
